LICENSE
README.md
nonebot_plugin_friends/__init__.py
nonebot_plugin_friends/config.py
nonebot_plugin_friends/event.py
nonebot_plugin_friends/matcher.py
nonebot_plugin_friends/rule.py
nonebot_plugin_friends/utils.py
nonebot_plugin_friends-0.1.4.dist-info/LICENSE
nonebot_plugin_friends-0.1.4.dist-info/METADATA
nonebot_plugin_friends-0.1.4.dist-info/WHEEL
nonebot_plugin_friends-0.1.4.dist-info/RECORD
