Metadata-Version: 2.1
Name: nonebot_plugin_friends
Version: 0.1.4
Summary: Nonebot2插件处理好友申请
Home-page: https://github.com/Agnes4m/nonebot_plugin_friends
License: MIT
Keywords: maimai,nonebot2,plugin
Author: Agnes_Digital
Author-email: Z735803792@163.com
Requires-Python: >=3.8,<4.0
Classifier: License :: OSI Approved :: MIT License
Classifier: Operating System :: OS Independent
Classifier: Programming Language :: Python
Classifier: Programming Language :: Python :: 3
Classifier: Programming Language :: Python :: 3.8
Classifier: Programming Language :: Python :: 3.9
Classifier: Programming Language :: Python :: 3.10
Classifier: Programming Language :: Python :: 3.11
Classifier: Programming Language :: Python :: 3.12
Requires-Dist: nonebot-adapter-onebot (>=2.1.3,<3.0.0)
Requires-Dist: nonebot2 (>=2.0.0,<3.0.0)
Project-URL: Repository, https://github.com/Agnes4m/nonebot_plugin_friends
